pydisco/__init__.py
pydisco/activity.py
pydisco/cache.py
pydisco/channel.py
pydisco/client.py
pydisco/emoji.py
pydisco/guild.py
pydisco/http.py
pydisco/intents.py
pydisco/member.py
pydisco/message.py
pydisco/presence.py
pydisco/role.py
pydisco/sticker.py
pydisco/user.py
pydisco/utils.py
pydisco/voice.py
pydiscoo-1.0.0a0.dist-info/LICENSE
pydiscoo-1.0.0a0.dist-info/METADATA
pydiscoo-1.0.0a0.dist-info/WHEEL
pydiscoo-1.0.0a0.dist-info/top_level.txt
pydiscoo-1.0.0a0.dist-info/RECORD
