Metadata-Version: 2.1
Name: pydiscoo
Version: 1.0.0a0
Summary: Another Discord Wrapper for Python. Simplified and powerful bots are here.
Home-page: https://github.com/Pelfox/pydisco
Author: Pelfox
Author-email: me@pelfox.dev
License: MIT
Platform: UNKNOWN
Classifier: License :: OSI Approved :: MIT License
Classifier: Operating System :: OS Independent
Classifier: Programming Language :: Python :: 3.8
Classifier: Programming Language :: Python :: 3.9
Classifier: Programming Language :: Python :: 3.10
Classifier: Topic :: Software Development :: Libraries
Classifier: Topic :: Software Development :: Libraries :: Python Modules
Requires-Python: >=3.8.0
License-File: LICENSE
Requires-Dist: aiohttp (>=3.8.1)
Requires-Dist: pylint (>=2.12.2)
Requires-Dist: pytest (>=7.1.1)
